MANIFEST.in
README.rst
setup.py
docs/HISTORY.txt
docs/INSTALL.txt
docs/LICENSE.ZPL
docs/LICENSE.txt
docs/SPONSORS.txt
psj/__init__.py
psj.policy.egg-info/PKG-INFO
psj.policy.egg-info/SOURCES.txt
psj.policy.egg-info/dependency_links.txt
psj.policy.egg-info/entry_points.txt
psj.policy.egg-info/namespace_packages.txt
psj.policy.egg-info/not-zip-safe
psj.policy.egg-info/requires.txt
psj.policy.egg-info/top_level.txt
psj/policy/__init__.py
psj/policy/setuphandlers.py
psj/policy/testing.py
psj/policy/tests/__init__.py
psj/policy/tests/test_doctests.py
psj/policy/transforms/__init__.py
psj/policy/transforms/cmd_oooconv.py
psj/policy/transforms/cmd_xsltproc.py
psj/policy/transforms/doc_to_html.py
psj/policy/transforms/doc_to_pdf.py
psj/policy/transforms/odt_to_html.py
psj/policy/transforms/odt_to_pdf.py
psj/policy/transforms/processors.py
psj/policy/transforms/xslttrans.py
psj/policy/transforms/tests/__init__.py
psj/policy/transforms/tests/test_cmd_oooconv.py
psj/policy/transforms/tests/test_doc_to_html.py
psj/policy/transforms/tests/test_doc_to_pdf.py
psj/policy/transforms/tests/test_odt_to_html.py
psj/policy/transforms/tests/test_odt_to_pdf.py
psj/policy/transforms/tests/test_processors.py
psj/policy/transforms/tests/test_transforms.py