Metadata-Version: 1.1
Name: psj.policy
Version: 1.1
Summary: Plone Scholarly Journal - the site policy
Home-page: http://pypi.python.org/pypi/psj.policy
Author: Uli Fouquet
Author-email: uli@gnufix.de
License: GPL
Keywords: zope policy scholarly scholar journal plone plone3 plone4
Platform: UNKNOWN
Classifier: Development Status :: 3 - Alpha
Classifier: Environment :: Web Environment
Classifier: Intended Audience :: Developers
Classifier: License :: OSI Approved :: Zope Public License
Classifier: Programming Language :: Python
Classifier: Operating System :: OS Independent
Classifier: Framework :: Plone
Classifier: Topic :: Software Development :: Libraries :: Python Modules
